setup.py
dho_distributions/Binomialdistribution.py
dho_distributions/Gaussiandistribution.py
dho_distributions/Generaldistribution.py
dho_distributions/__init__.py
dho_distributions.egg-info/PKG-INFO
dho_distributions.egg-info/SOURCES.txt
dho_distributions.egg-info/dependency_links.txt
dho_distributions.egg-info/not-zip-safe
dho_distributions.egg-info/top_level.txt