Metadata-Version: 1.0
Name: dho-distributions
Version: 0.1
Summary: Gaussian distributions
Home-page: UNKNOWN
Author: Dan Hernandez
Author-email: UNKNOWN
License: UNKNOWN
Platform: UNKNOWN
